rockai_cli_app/__init__.py
rockai_cli_app/command/__init__.py
rockai_cli_app/command/openapi_schema.py
rockai_cli_app/data_class.py
rockai_cli_app/docker/__init__.py
rockai_cli_app/docker/docker_util.py
rockai_cli_app/docker/tf_compat.json
rockai_cli_app/docker/torch_compat.json
rockai_cli_app/docker/torch_version.py
rockai_cli_app/parser/__init__.py
rockai_cli_app/parser/config_util.py
rockai_cli_app/predictor.py
rockai_cli_app/rock.py
rockai_cli_app/server/__init__.py
rockai_cli_app/server/files.py
rockai_cli_app/server/http.py
rockai_cli_app/server/json.py
rockai_cli_app/server/runner.py
rockai_cli_app/server/types.py
rockai_cli_app/server/utils.py
rockai_cli_app/test.py
rockai_cli_app-0.2.130.dist-info/LICENSE
rockai_cli_app-0.2.130.dist-info/METADATA
rockai_cli_app-0.2.130.dist-info/WHEEL
rockai_cli_app-0.2.130.dist-info/entry_points.txt
rockai_cli_app-0.2.130.dist-info/RECORD
