Metadata-Version: 2.1
Name: rockai-cli-app
Version: 0.2.130
Summary: Python SDK for RockAI.online
Author: RockAI
Author-email: admin@example.com
Requires-Python: >=3.9,<3.12
Classifier: Programming Language :: Python :: 3
Classifier: Programming Language :: Python :: 3.9
Classifier: Programming Language :: Python :: 3.10
Classifier: Programming Language :: Python :: 3.11
Requires-Dist: aiohttp-sse-client (==0.2.1)
Requires-Dist: aiosseclient (>=0.1.3,<0.2.0)
Requires-Dist: fastapi (>=0.109.2,<0.110.0)
Requires-Dist: httpx (>=0.27.0,<0.28.0)
Requires-Dist: httpx-sse (==0.1.0)
Requires-Dist: multiprocess (>=0.70.16,<0.71.0)
Requires-Dist: pebble (>=5.0.7,<6.0.0)
Requires-Dist: requests (>=2.31.0,<3.0.0)
Requires-Dist: sseclient (>=0.0.27,<0.0.28)
Requires-Dist: toml (>=0.10.2,<0.11.0)
Requires-Dist: typer[all] (>=0.12.3,<0.13.0)
Requires-Dist: uvicorn[standard] (>=0.27.0.post1,<0.28.0)
